{
  "colorGroups": [
    {
      "query": "tag:#community/Custom_QR_Engine",
      "color": {
        "a": 1,
        "rgb": 5142951
      }
    },
    {
      "query": "tag:#community/QR_Engine_&_Export",
      "color": {
        "a": 1,
        "rgb": 15896107
      }
    },
    {
      "query": "tag:#community/README_Features",
      "color": {
        "a": 1,
        "rgb": 14767961
      }
    },
    {
      "query": "tag:#community/Legacy_Docs_Hub",
      "color": {
        "a": 1,
        "rgb": 7780274
      }
    },
    {
      "query": "tag:#community/Deployment_&_Branding",
      "color": {
        "a": 1,
        "rgb": 5873999
      }
    },
    {
      "query": "tag:#community/QR_Data_Service",
      "color": {
        "a": 1,
        "rgb": 15583560
      }
    },
    {
      "query": "tag:#community/Custom_QR_Styles",
      "color": {
        "a": 1,
        "rgb": 11565729
      }
    },
    {
      "query": "tag:#community/QR_Preview_&_Payloads",
      "color": {
        "a": 1,
        "rgb": 16752039
      }
    },
    {
      "query": "tag:#community/Preview_&_Display",
      "color": {
        "a": 1,
        "rgb": 10253663
      }
    },
    {
      "query": "tag:#community/Favicon_Branding",
      "color": {
        "a": 1,
        "rgb": 12234924
      }
    },
    {
      "query": "tag:#community/Theme_Toggle",
      "color": {
        "a": 1,
        "rgb": 5142951
      }
    },
    {
      "query": "tag:#community/Error_Boundary",
      "color": {
        "a": 1,
        "rgb": 15896107
      }
    },
    {
      "query": "tag:#community/QR_Form",
      "color": {
        "a": 1,
        "rgb": 14767961
      }
    },
    {
      "query": "tag:#community/React_19",
      "color": {
        "a": 1,
        "rgb": 7780274
      }
    },
    {
      "query": "tag:#community/Batch_Generator",
      "color": {
        "a": 1,
        "rgb": 5873999
      }
    },
    {
      "query": "tag:#community/Wizard_Content",
      "color": {
        "a": 1,
        "rgb": 15583560
      }
    },
    {
      "query": "tag:#community/QR_Data_Generation",
      "color": {
        "a": 1,
        "rgb": 11565729
      }
    },
    {
      "query": "tag:#community/Footer_Component",
      "color": {
        "a": 1,
        "rgb": 16752039
      }
    },
    {
      "query": "tag:#community/App_Root",
      "color": {
        "a": 1,
        "rgb": 10253663
      }
    },
    {
      "query": "tag:#community/History_Drawer",
      "color": {
        "a": 1,
        "rgb": 12234924
      }
    },
    {
      "query": "tag:#community/Customization_Panel",
      "color": {
        "a": 1,
        "rgb": 5142951
      }
    },
    {
      "query": "tag:#community/QR_Studio_Entry",
      "color": {
        "a": 1,
        "rgb": 15896107
      }
    },
    {
      "query": "tag:#community/Legacy_App",
      "color": {
        "a": 1,
        "rgb": 14767961
      }
    },
    {
      "query": "tag:#community/QR_Service_Functions",
      "color": {
        "a": 1,
        "rgb": 7780274
      }
    },
    {
      "query": "tag:#community/App_Root_Component",
      "color": {
        "a": 1,
        "rgb": 5873999
      }
    },
    {
      "query": "tag:#community/Custom_QR_Component",
      "color": {
        "a": 1,
        "rgb": 15583560
      }
    },
    {
      "query": "tag:#community/Web_Vitals",
      "color": {
        "a": 1,
        "rgb": 11565729
      }
    },
    {
      "query": "tag:#community/Glass_Background",
      "color": {
        "a": 1,
        "rgb": 16752039
      }
    },
    {
      "query": "tag:#community/Type_Icons",
      "color": {
        "a": 1,
        "rgb": 10253663
      }
    },
    {
      "query": "tag:#community/Wizard_Design_Step",
      "color": {
        "a": 1,
        "rgb": 12234924
      }
    },
    {
      "query": "tag:#community/Wizard_Type_Step",
      "color": {
        "a": 1,
        "rgb": 5142951
      }
    },
    {
      "query": "tag:#community/Utils",
      "color": {
        "a": 1,
        "rgb": 15896107
      }
    },
    {
      "query": "tag:#community/Graph_Report",
      "color": {
        "a": 1,
        "rgb": 14767961
      }
    },
    {
      "query": "tag:#community/Legacy_Footer",
      "color": {
        "a": 1,
        "rgb": 7780274
      }
    },
    {
      "query": "tag:#community/Live_Preview",
      "color": {
        "a": 1,
        "rgb": 5873999
      }
    },
    {
      "query": "tag:#community/QR_Engine_Docs",
      "color": {
        "a": 1,
        "rgb": 15583560
      }
    },
    {
      "query": "tag:#community/QR_Display",
      "color": {
        "a": 1,
        "rgb": 11565729
      }
    },
    {
      "query": "tag:#community/QR_Customization",
      "color": {
        "a": 1,
        "rgb": 16752039
      }
    },
    {
      "query": "tag:#community/Report_Web_Vitals",
      "color": {
        "a": 1,
        "rgb": 10253663
      }
    },
    {
      "query": "tag:#community/App_Entry_Point",
      "color": {
        "a": 1,
        "rgb": 12234924
      }
    },
    {
      "query": "tag:#community/App_Test_Suite",
      "color": {
        "a": 1,
        "rgb": 5142951
      }
    },
    {
      "query": "tag:#community/Test_Setup",
      "color": {
        "a": 1,
        "rgb": 15896107
      }
    },
    {
      "query": "tag:#community/Robots.txt",
      "color": {
        "a": 1,
        "rgb": 14767961
      }
    },
    {
      "query": "tag:#community/Vite_Config",
      "color": {
        "a": 1,
        "rgb": 7780274
      }
    },
    {
      "query": "tag:#community/Vite_Env_Types",
      "color": {
        "a": 1,
        "rgb": 5873999
      }
    },
    {
      "query": "tag:#community/Glass_Card",
      "color": {
        "a": 1,
        "rgb": 15583560
      }
    },
    {
      "query": "tag:#community/Header_Layout",
      "color": {
        "a": 1,
        "rgb": 11565729
      }
    },
    {
      "query": "tag:#community/QR_Canvas",
      "color": {
        "a": 1,
        "rgb": 16752039
      }
    },
    {
      "query": "tag:#community/Button_UI",
      "color": {
        "a": 1,
        "rgb": 10253663
      }
    },
    {
      "query": "tag:#community/Dialog_UI",
      "color": {
        "a": 1,
        "rgb": 12234924
      }
    },
    {
      "query": "tag:#community/Input_UI",
      "color": {
        "a": 1,
        "rgb": 5142951
      }
    },
    {
      "query": "tag:#community/Label_UI",
      "color": {
        "a": 1,
        "rgb": 15896107
      }
    },
    {
      "query": "tag:#community/Progress_UI",
      "color": {
        "a": 1,
        "rgb": 14767961
      }
    },
    {
      "query": "tag:#community/Radio_Group_UI",
      "color": {
        "a": 1,
        "rgb": 7780274
      }
    },
    {
      "query": "tag:#community/Select_UI",
      "color": {
        "a": 1,
        "rgb": 5873999
      }
    },
    {
      "query": "tag:#community/Slider_UI",
      "color": {
        "a": 1,
        "rgb": 15583560
      }
    },
    {
      "query": "tag:#community/Switch_UI",
      "color": {
        "a": 1,
        "rgb": 11565729
      }
    },
    {
      "query": "tag:#community/Tabs_UI",
      "color": {
        "a": 1,
        "rgb": 16752039
      }
    },
    {
      "query": "tag:#community/Textarea_UI",
      "color": {
        "a": 1,
        "rgb": 10253663
      }
    },
    {
      "query": "tag:#community/Tooltip_UI",
      "color": {
        "a": 1,
        "rgb": 12234924
      }
    },
    {
      "query": "tag:#community/Stepper",
      "color": {
        "a": 1,
        "rgb": 5142951
      }
    },
    {
      "query": "tag:#community/Wizard_Shell",
      "color": {
        "a": 1,
        "rgb": 15896107
      }
    },
    {
      "query": "tag:#community/History_Store",
      "color": {
        "a": 1,
        "rgb": 14767961
      }
    },
    {
      "query": "tag:#community/Wizard_Store",
      "color": {
        "a": 1,
        "rgb": 7780274
      }
    },
    {
      "query": "tag:#community/Legacy_Index",
      "color": {
        "a": 1,
        "rgb": 5873999
      }
    },
    {
      "query": "tag:#community/Setup_Tests",
      "color": {
        "a": 1,
        "rgb": 15583560
      }
    }
  ]
}